pyparallel.py
setup.py
py_parallel.egg-info/PKG-INFO
py_parallel.egg-info/SOURCES.txt
py_parallel.egg-info/dependency_links.txt
py_parallel.egg-info/top_level.txt