Metadata-Version: 1.0
Name: py-parallel
Version: 1.0.0
Summary: Utility for simple asynchronous function calls
Home-page: http://github.com/Shapeways/py-parallel
Author: Shapeways
Author-email: api@shapeways.com
License: UNKNOWN
Platform: UNKNOWN
